wgt/__init__.py
wgt/wgt.py
wgt-0.3.1.dist-info/METADATA
wgt-0.3.1.dist-info/WHEEL
wgt-0.3.1.dist-info/entry_points.txt
wgt-0.3.1.dist-info/top_level.txt
wgt-0.3.1.dist-info/RECORD
