Metadata-Version: 2.2
Name: wgt
Version: 0.3.1
Summary: Command line tool for quick API testing
Author-email: Daniel Hjertholm <8713259+danhje@users.noreply.github.com>
Requires-Python: >=3.9
Requires-Dist: requests
Requires-Dist: toolz
Requires-Dist: rich
